pinttr/__init__.py
pinttr/_context.py
pinttr/_defaults.py
pinttr/_func.py
pinttr/_generator.py
pinttr/_interpret.py
pinttr/_make.py
pinttr/_metadata.py
pinttr/_next_gen.py
pinttr/_version.py
pinttr/converters.py
pinttr/exceptions.py
pinttr/util.py
pinttr/validators.py
pinttrs/__init__.py
pinttrs/__init__.pyi
pinttrs/converters.py
pinttrs/exceptions.py
pinttrs/util.py
pinttrs/validators.py
pinttrs-25.1.0.dist-info/METADATA
pinttrs-25.1.0.dist-info/WHEEL
pinttrs-25.1.0.dist-info/licenses/LICENSE
pinttrs-25.1.0.dist-info/RECORD
