Metadata-Version: 2.4
Name: pinttrs
Version: 25.1.0
Summary: Pint meets attrs.
Project-URL: Changelog, https://github.com/rayference/pinttrs/blob/main/CHANGELOG.md
Project-URL: Documentation, https://pinttrs.readthedocs.io
Project-URL: Homepage, https://github.com/rayference/pinttrs
Project-URL: Issues, https://github.com/rayference/pinttrs/issues
Project-URL: Repository, https://github.com/rayference/pinttrs
Author-email: Vincent Leroy <vincent.leroy@rayference.eu>
License: MIT
License-File: LICENSE
Classifier: Development Status :: 6 - Mature
Classifier: License :: OSI Approved :: MIT License
Classifier: Programming Language :: Python :: 3.8
Classifier: Programming Language :: Python :: 3.9
Classifier: Programming Language :: Python :: 3.10
Classifier: Programming Language :: Python :: 3.11
Classifier: Programming Language :: Python :: 3.12
Classifier: Programming Language :: Python :: 3.13
Classifier: Topic :: Scientific/Engineering
Requires-Python: >=3.8
Requires-Dist: attrs>=21.3
Requires-Dist: pint>=0.16
